{
  "ship_classes": [
    {
      "platform": "Nimitz-class CVN",
      "ship_type": "Aircraft Carrier",
      "ship_class": "Nimitz",
      "ship_role": "Power Projection",
      "category": "Military Capital Ship",
      "affiliation": "MILITARY",
      "length_meters": 332.8,
      "beam_meters": 76.8,
      "draft_meters": 11.3,
      "displacement_tons": 100000,
      "max_speed_kts": 30,
      "typical_speed_kts": 20,
      "expected_instances": 11
    },
    {
      "platform": "Ford-class CVN",
      "ship_type": "Aircraft Carrier",
      "ship_class": "Gerald R. Ford",
      "ship_role": "Power Projection",
      "category": "Military Capital Ship",
      "affiliation": "MILITARY",
      "length_meters": 337.0,
      "beam_meters": 78.0,
      "draft_meters": 12.0,
      "displacement_tons": 100000,
      "max_speed_kts": 30,
      "typical_speed_kts": 20,
      "expected_instances": 3
    },
    {
      "platform": "Arleigh Burke-class DDG",
      "ship_type": "Destroyer",
      "ship_class": "Arleigh Burke",
      "ship_role": "Surface Warfare",
      "category": "Military Combatant",
      "affiliation": "MILITARY",
      "length_meters": 154.0,
      "beam_meters": 20.0,
      "draft_meters": 6.3,
      "displacement_tons": 9000,
      "max_speed_kts": 32,
      "typical_speed_kts": 20,
      "expected_instances": 70
    },
    {
      "platform": "Ticonderoga-class CG",
      "ship_type": "Cruiser",
      "ship_class": "Ticonderoga",
      "ship_role": "Air Defense",
      "category": "Military Combatant",
      "affiliation": "MILITARY",
      "length_meters": 173.0,
      "beam_meters": 16.8,
      "draft_meters": 10.2,
      "displacement_tons": 9800,
      "max_speed_kts": 32,
      "typical_speed_kts": 20,
      "expected_instances": 22
    },
    {
      "platform": "Virginia-class SSN",
      "ship_type": "Submarine",
      "ship_class": "Virginia",
      "ship_role": "Attack Submarine",
      "category": "Military Submarine",
      "affiliation": "MILITARY",
      "length_meters": 115.0,
      "beam_meters": 10.4,
      "draft_meters": 9.8,
      "displacement_tons": 7800,
      "max_speed_kts": 25,
      "typical_speed_kts": 12,
      "expected_instances": 20
    },
    {
      "platform": "Ohio-class SSBN",
      "ship_type": "Submarine",
      "ship_class": "Ohio",
      "ship_role": "Ballistic Missile Submarine",
      "category": "Military Submarine",
      "affiliation": "MILITARY",
      "length_meters": 170.0,
      "beam_meters": 12.8,
      "draft_meters": 10.8,
      "displacement_tons": 18750,
      "max_speed_kts": 20,
      "typical_speed_kts": 12,
      "expected_instances": 14
    },
    {
      "platform": "Freedom-class LCS",
      "ship_type": "Littoral Combat Ship",
      "ship_class": "Freedom",
      "ship_role": "Littoral Operations",
      "category": "Military Combatant",
      "affiliation": "MILITARY",
      "length_meters": 115.0,
      "beam_meters": 17.5,
      "draft_meters": 3.7,
      "displacement_tons": 3500,
      "max_speed_kts": 45,
      "typical_speed_kts": 25,
      "expected_instances": 8
    },
    {
      "platform": "Independence-class LCS",
      "ship_type": "Littoral Combat Ship",
      "ship_class": "Independence",
      "ship_role": "Littoral Operations",
      "category": "Military Combatant",
      "affiliation": "MILITARY",
      "length_meters": 127.4,
      "beam_meters": 31.6,
      "draft_meters": 4.3,
      "displacement_tons": 3100,
      "max_speed_kts": 44,
      "typical_speed_kts": 25,
      "expected_instances": 10
    },
    {
      "platform": "America-class LHA",
      "ship_type": "Amphibious Assault Ship",
      "ship_class": "America",
      "ship_role": "Amphibious Warfare",
      "category": "Military Amphibious",
      "affiliation": "MILITARY",
      "length_meters": 257.3,
      "beam_meters": 32.3,
      "draft_meters": 8.2,
      "displacement_tons": 45000,
      "max_speed_kts": 22,
      "typical_speed_kts": 15,
      "expected_instances": 3
    },
    {
      "platform": "Wasp-class LHD",
      "ship_type": "Amphibious Assault Ship",
      "ship_class": "Wasp",
      "ship_role": "Amphibious Warfare",
      "category": "Military Amphibious",
      "affiliation": "MILITARY",
      "length_meters": 257.3,
      "beam_meters": 32.3,
      "draft_meters": 8.2,
      "displacement_tons": 40500,
      "max_speed_kts": 22,
      "typical_speed_kts": 15,
      "expected_instances": 8
    },
    {
      "platform": "Type 45 Destroyer",
      "ship_type": "Destroyer",
      "ship_class": "Type 45",
      "ship_role": "Air Defense",
      "category": "Military Combatant",
      "affiliation": "MILITARY",
      "length_meters": 152.4,
      "beam_meters": 21.2,
      "draft_meters": 7.4,
      "displacement_tons": 8500,
      "max_speed_kts": 29,
      "typical_speed_kts": 18,
      "expected_instances": 6
    },
    {
      "platform": "Type 26 Frigate",
      "ship_type": "Frigate",
      "ship_class": "Type 26",
      "ship_role": "Anti-Submarine Warfare",
      "category": "Military Combatant",
      "affiliation": "MILITARY",
      "length_meters": 149.9,
      "beam_meters": 20.8,
      "draft_meters": 7.0,
      "displacement_tons": 8000,
      "max_speed_kts": 26,
      "typical_speed_kts": 18,
      "expected_instances": 8
    },
    {
      "platform": "VLCC Tanker",
      "ship_type": "Tanker",
      "ship_class": "VLCC",
      "ship_role": "Crude Oil Transport",
      "category": "Commercial Tanker",
      "affiliation": "CIVILIAN",
      "length_meters": 330.0,
      "beam_meters": 60.0,
      "draft_meters": 22.0,
      "displacement_tons": 320000,
      "max_speed_kts": 16,
      "typical_speed_kts": 13,
      "expected_instances": 40
    },
    {
      "platform": "Suezmax Tanker",
      "ship_type": "Tanker",
      "ship_class": "Suezmax",
      "ship_role": "Crude Oil Transport",
      "category": "Commercial Tanker",
      "affiliation": "CIVILIAN",
      "length_meters": 275.0,
      "beam_meters": 50.0,
      "draft_meters": 16.0,
      "displacement_tons": 160000,
      "max_speed_kts": 15,
      "typical_speed_kts": 13,
      "expected_instances": 30
    },
    {
      "platform": "Maersk Triple-E",
      "ship_type": "Container Ship",
      "ship_class": "Triple-E",
      "ship_role": "Container Transport",
      "category": "Commercial Container",
      "affiliation": "CIVILIAN",
      "length_meters": 399.0,
      "beam_meters": 59.0,
      "draft_meters": 16.0,
      "displacement_tons": 220000,
      "max_speed_kts": 23,
      "typical_speed_kts": 19,
      "expected_instances": 30
    },
    {
      "platform": "New Panamax Container",
      "ship_type": "Container Ship",
      "ship_class": "New Panamax",
      "ship_role": "Container Transport",
      "category": "Commercial Container",
      "affiliation": "CIVILIAN",
      "length_meters": 366.0,
      "beam_meters": 49.0,
      "draft_meters": 15.2,
      "displacement_tons": 120000,
      "max_speed_kts": 24,
      "typical_speed_kts": 20,
      "expected_instances": 40
    },
    {
      "platform": "Panamax Container",
      "ship_type": "Container Ship",
      "ship_class": "Panamax",
      "ship_role": "Container Transport",
      "category": "Commercial Container",
      "affiliation": "CIVILIAN",
      "length_meters": 294.0,
      "beam_meters": 32.3,
      "draft_meters": 12.0,
      "displacement_tons": 70000,
      "max_speed_kts": 24,
      "typical_speed_kts": 20,
      "expected_instances": 35
    },
    {
      "platform": "LNG Carrier Q-Max",
      "ship_type": "LNG Carrier",
      "ship_class": "Q-Max",
      "ship_role": "Liquefied Natural Gas",
      "category": "Commercial Gas Carrier",
      "affiliation": "CIVILIAN",
      "length_meters": 345.0,
      "beam_meters": 53.8,
      "draft_meters": 12.0,
      "displacement_tons": 165000,
      "max_speed_kts": 19,
      "typical_speed_kts": 17,
      "expected_instances": 15
    },
    {
      "platform": "LNG Carrier Conventional",
      "ship_type": "LNG Carrier",
      "ship_class": "LNG-C",
      "ship_role": "Liquefied Natural Gas",
      "category": "Commercial Gas Carrier",
      "affiliation": "CIVILIAN",
      "length_meters": 280.0,
      "beam_meters": 43.0,
      "draft_meters": 11.5,
      "displacement_tons": 95000,
      "max_speed_kts": 19,
      "typical_speed_kts": 17,
      "expected_instances": 20
    },
    {
      "platform": "Capesize Bulk Carrier",
      "ship_type": "Bulk Carrier",
      "ship_class": "Capesize",
      "ship_role": "Dry Bulk Transport",
      "category": "Commercial Bulk",
      "affiliation": "CIVILIAN",
      "length_meters": 290.0,
      "beam_meters": 45.0,
      "draft_meters": 18.0,
      "displacement_tons": 180000,
      "max_speed_kts": 14,
      "typical_speed_kts": 12,
      "expected_instances": 25
    },
    {
      "platform": "Panamax Bulk Carrier",
      "ship_type": "Bulk Carrier",
      "ship_class": "Panamax Bulk",
      "ship_role": "Dry Bulk Transport",
      "category": "Commercial Bulk",
      "affiliation": "CIVILIAN",
      "length_meters": 225.0,
      "beam_meters": 32.2,
      "draft_meters": 12.5,
      "displacement_tons": 75000,
      "max_speed_kts": 14,
      "typical_speed_kts": 12,
      "expected_instances": 20
    },
    {
      "platform": "Ro-Ro Ferry",
      "ship_type": "Ferry",
      "ship_class": "Ro-Ro",
      "ship_role": "Vehicle/Passenger Ferry",
      "category": "Commercial Ferry",
      "affiliation": "CIVILIAN",
      "length_meters": 200.0,
      "beam_meters": 26.0,
      "draft_meters": 6.5,
      "displacement_tons": 25000,
      "max_speed_kts": 22,
      "typical_speed_kts": 18,
      "expected_instances": 15
    },
    {
      "platform": "Cruise Ship Oasis-class",
      "ship_type": "Cruise Ship",
      "ship_class": "Oasis",
      "ship_role": "Passenger Cruise",
      "category": "Commercial Cruise",
      "affiliation": "CIVILIAN",
      "length_meters": 360.0,
      "beam_meters": 60.5,
      "draft_meters": 9.3,
      "displacement_tons": 100000,
      "max_speed_kts": 22,
      "typical_speed_kts": 20,
      "expected_instances": 8
    },
    {
      "platform": "Offshore Supply Vessel",
      "ship_type": "Support Vessel",
      "ship_class": "OSV",
      "ship_role": "Offshore Support",
      "category": "Commercial Support",
      "affiliation": "CIVILIAN",
      "length_meters": 90.0,
      "beam_meters": 22.0,
      "draft_meters": 7.5,
      "displacement_tons": 5000,
      "max_speed_kts": 14,
      "typical_speed_kts": 11,
      "expected_instances": 20
    },
    {
      "platform": "USCG Legend-class NSC",
      "ship_type": "Coast Guard Cutter",
      "ship_class": "Legend",
      "ship_role": "Law Enforcement/SAR",
      "category": "Coast Guard",
      "affiliation": "MILITARY",
      "length_meters": 127.0,
      "beam_meters": 16.4,
      "draft_meters": 6.9,
      "displacement_tons": 4500,
      "max_speed_kts": 28,
      "typical_speed_kts": 18,
      "expected_instances": 11
    }
  ]
}
